autoqrels/__init__.py
autoqrels/labeler.py
autoqrels/text.py
autoqrels/oneshot/__init__.py
autoqrels/oneshot/duoprompt.py
autoqrels/oneshot/duot5.py
autoqrels/oneshot/maxrep.py
autoqrels/oneshot/oneshot_labeler.py
autoqrels/zeroshot/__init__.py
autoqrels/zeroshot/gradedmonoprompt.py
autoqrels/zeroshot/zeroshot_labeler.py
autoqrels-0.0.1.dist-info/LICENSE
autoqrels-0.0.1.dist-info/METADATA
autoqrels-0.0.1.dist-info/WHEEL
autoqrels-0.0.1.dist-info/top_level.txt
autoqrels-0.0.1.dist-info/RECORD
