Metadata-Version: 2.1
Name: autoqrels
Version: 0.0.1
Summary: a tool for automatically inferring query relevance assessments (qrels)
Home-page: https://github.com/seanmacavaney/autoqrels
Author: Sean MacAvaney
Author-email: sean.macavaney@glasgow.ac.uk
Requires-Python: >=3.6
License-File: LICENSE
Requires-Dist: ir-measures >=0.3.2
Requires-Dist: ir-datasets
Requires-Dist: transformers
Requires-Dist: more-itertools
Requires-Dist: pandas
Requires-Dist: smashed
